jupyter_mynerva/__init__.py
jupyter_mynerva/_version.py
jupyter_mynerva/routes.py
jupyter_mynerva-0.1.2.data/data/etc/jupyter/jupyter_server_config.d/jupyter_mynerva.json
jupyter_mynerva-0.1.2.data/data/share/jupyter/labextensions/jupyter-mynerva/package.json
jupyter_mynerva-0.1.2.data/data/share/jupyter/labextensions/jupyter-mynerva/schemas/jupyter-mynerva/package.json.orig
jupyter_mynerva-0.1.2.data/data/share/jupyter/labextensions/jupyter-mynerva/schemas/jupyter-mynerva/plugin.json
jupyter_mynerva-0.1.2.data/data/share/jupyter/labextensions/jupyter-mynerva/static/364.971bfbe72c2840c5a0d4.js
jupyter_mynerva-0.1.2.data/data/share/jupyter/labextensions/jupyter-mynerva/static/47.d9ee1aa4d94755627c10.js
jupyter_mynerva-0.1.2.data/data/share/jupyter/labextensions/jupyter-mynerva/static/678.b745814ffbfc7d0bc280.js
jupyter_mynerva-0.1.2.data/data/share/jupyter/labextensions/jupyter-mynerva/static/remoteEntry.696ed8cf2ffc4cd887b6.js
jupyter_mynerva-0.1.2.data/data/share/jupyter/labextensions/jupyter-mynerva/static/style.js
jupyter_mynerva-0.1.2.data/data/share/jupyter/labextensions/jupyter-mynerva/static/third-party-licenses.json
jupyter_mynerva-0.1.2.data/data/share/jupyter/labextensions/jupyter-mynerva/install.json
jupyter_mynerva-0.1.2.dist-info/METADATA
jupyter_mynerva-0.1.2.dist-info/WHEEL
jupyter_mynerva-0.1.2.dist-info/licenses/LICENSE
jupyter_mynerva-0.1.2.dist-info/RECORD
