Metadata-Version: 2.4
Name: jupyter_mynerva
Version: 0.1.2
Summary: A JupyterLab extension that provides an LLM-powered assistant with deep understanding of notebook structure.
Project-URL: Homepage, https://github.com/yacchin1205/jupyter-mynerva
Project-URL: Bug Tracker, https://github.com/yacchin1205/jupyter-mynerva/issues
Project-URL: Repository, https://github.com/yacchin1205/jupyter-mynerva.git
Author: yacchin1205
License: BSD 3-Clause License
License-File: LICENSE
Keywords: jupyter,jupyterlab,jupyterlab-extension
Classifier: Framework :: Jupyter
Classifier: Framework :: Jupyter :: JupyterLab
Classifier: Framework :: Jupyter :: JupyterLab :: 4
Classifier: Framework :: Jupyter :: JupyterLab :: Extensions
Classifier: Framework :: Jupyter :: JupyterLab :: Extensions :: Prebuilt
Classifier: License :: OSI Approved :: BSD License
Classifier: Programming Language :: Python
Classifier: Programming Language :: Python :: 3
Classifier: Programming Language :: Python :: 3.10
Classifier: Programming Language :: Python :: 3.11
Classifier: Programming Language :: Python :: 3.12
Classifier: Programming Language :: Python :: 3.13
Classifier: Programming Language :: Python :: 3.14
Requires-Python: >=3.10
Requires-Dist: anthropic>=0.30.0
Requires-Dist: cryptography>=41.0.0
Requires-Dist: jupyter-server<3,>=2.4.0
Requires-Dist: openai>=1.0.0
Requires-Dist: tomli>=2.0.0; python_version < '3.11'
